djstarter/__init__.py
djstarter/admin.py
djstarter/apps.py
djstarter/clients.py
djstarter/decorators.py
djstarter/exceptions.py
djstarter/management/__init__.py
djstarter/management/commands/__init__.py
djstarter/management/commands/create_db.py
djstarter/management/commands/print_env_vars.py
djstarter/managers.py
djstarter/migrations/0001_initial.py
djstarter/migrations/0002_task.py
djstarter/migrations/__init__.py
djstarter/models.py
djstarter/tests/__init__.py
djstarter/tests/test_clients.py
djstarter/tests/test_decorators.py
djstarter/tests/test_managers.py
djstarter/tests/test_models.py
djstarter/tests/test_utils.py
djstarter/utils.py
dj_starter-0.1.17.dist-info/METADATA
dj_starter-0.1.17.dist-info/WHEEL
dj_starter-0.1.17.dist-info/RECORD
